arborist/__init__.py
arborist/climate_change.py
arborist/electricity_grid.py
arborist/entsoe.py
arborist/exiobase_metadata.py
arborist/exiobase_us_epa.py
arborist/extract_metadata.py
arborist/filesystem.py
arborist/foaf.py
arborist/graph_common.py
arborist/time_uris.py
arborist/unit_uris.py
arborist/units.py
arborist/us_epa.py
arborist/us_epa_elem_flow_list.py
arborist/data/USEPA_URI.csv
arborist/data/climate_change.csv
arborist/data/exiobase_classifications_v_3_3_17.xlsx
arborist/data/exiobase_location_uris.csv
arborist/data/exiobase_to_usepa_ghg.csv
arborist-0.3.dist-info/LICENSE
arborist-0.3.dist-info/METADATA
arborist-0.3.dist-info/WHEEL
arborist-0.3.dist-info/entry_points.txt
arborist-0.3.dist-info/top_level.txt
arborist-0.3.dist-info/RECORD
