Metadata-Version: 2.1
Name: arborist
Version: 0.3
Summary: Generate the URIs needed for the BONSAI knowledge graph
Home-page: https://github.com/BONSAMURAIS/arborist
Author: BONSAI team
Author-email: info@bonsai.uno
License: BSD 3-Clause License
Requires-Dist: docopt
Requires-Dist: pandas
Requires-Dist: rdflib
Requires-Dist: xlrd
